README.md
setup.py
dort/__init__.py
dort/exceptions.py
dort.egg-info/PKG-INFO
dort.egg-info/SOURCES.txt
dort.egg-info/dependency_links.txt
dort.egg-info/requires.txt
dort.egg-info/top_level.txt
dort/captcha/__init__.py
dort/captcha/funcaptcha.py
dort/captcha/hcaptcha.py
dort/captcha/recaptcha.py
dort/captcha/task.py
dort/mail/__init__.py
dort/mail/mail.py