Metadata-Version: 2.1
Name: dort
Version: 1.3
Summary: dort solver/email api wrapper for python
Home-page: https://github.com/chaarlottte/dortsolver-python-api
Author: chaarlottte
